iopenscad/__init__.py
iopenscad/__main__.py
iopenscad/install.py
iopenscad/kernel.py
iopenscad/parser.py
iopenscad/scanner.py
iopenscad/openscad/kernel.json
iopenscad/openscad/logo-32x32.png
iopenscad/openscad/logo-64x64.png
jupyter_openscad_kernel-1.0.14.dist-info/METADATA
jupyter_openscad_kernel-1.0.14.dist-info/WHEEL
jupyter_openscad_kernel-1.0.14.dist-info/top_level.txt
jupyter_openscad_kernel-1.0.14.dist-info/RECORD
